fw_gear_dcm_to_mips/__init__.py
fw_gear_dcm_to_mips/intergration.py
fw_gear_dcm_to_mips/parser.py
fw_gear_dcm_to_mips-0.1.3.dist-info/METADATA
fw_gear_dcm_to_mips-0.1.3.dist-info/WHEEL
fw_gear_dcm_to_mips-0.1.3.dist-info/RECORD
