Metadata-Version: 2.4
Name: fw-gear-dcm-to-mips
Version: 0.1.3
Summary: Convert dicom file to MIPS format
Author-email: Flywheel <support@flywheel.io>
License-Expression: MIT
Requires-Python: <3.13,>=3.12
Requires-Dist: flywheel-gear-toolkit<0.7,>=0.6.10
Requires-Dist: fw-gear-dcm2niix<3,>=2.1.9
Requires-Dist: fw-gear-nifti-to-mips<0.2,>=0.1.1
Requires-Dist: pillow<11,>=10
